[
  {
    "title": "Climate Night Live at Climate Week NYC",
    "link": "https://climatenightlive.eventbrite.com",
    "summary": "We're kicking off Climate Week NYC with an evening of connection and clean energy entertainment. Sponsor spotlight: The business case for sustainability Volts live podcast: A conversation with Michael Liebreich Climate Night Live is back! By registering for this event, your contact details may be shared with the event's sponsor(s). Contact us at sponsorships@canarymedia.com to learn more about opportunities at this event.",
    "source": "Canary Media",
    "date": "2025-09-04",
    "timestamp": "2025-09-04T01:24:01.738893",
    "categories": "innovation,climate"
  },
  {
    "title": "The Grid's Two-Way Street: Engaging Customers for a Resilient Future",
    "link": "https://www.dnv.com/",
    "summary": "",
    "source": "Canary Media",
    "date": "2025-09-04",
    "timestamp": "2025-09-04T01:24:02.122057",
    "categories": "innovation"
  },
  {
    "title": "A New Era of Energy Efficiency: Innovations for Today and Tomorrow",
    "link": "https://energy.canarymedia.com/new-era-of-energy-efficiency",
    "summary": "",
    "source": "Canary Media",
    "date": "2025-09-04",
    "timestamp": "2025-09-04T01:24:02.415723",
    "categories": "innovation"
  },
  {
    "title": "Scaling Technological Greenhouse Gas Removal: A Global Roadmap to 2050",
    "link": "https://energy.canarymedia.com/rmi-scaling-technological-ghg-removal-v2",
    "summary": "",
    "source": "Canary Media",
    "date": "2025-09-04",
    "timestamp": "2025-09-04T01:24:02.520327",
    "categories": "policy,climate"
  },
  {
    "title": "Breaking Barriers in Carbon Dioxide Removal with Electrochemistry",
    "link": "https://energy.canarymedia.com/httpsrmi-breaking-barriers-cdr-v2",
    "summary": "",
    "source": "Canary Media",
    "date": "2025-09-04",
    "timestamp": "2025-09-04T01:24:02.663851",
    "categories": "climate"
  },
  {
    "title": "4\n\nTrump\u2019s push to keep coal plants running could cost consumers billions",
    "link": "https://www.canarymedia.com/articles/fossil-fuels/cost-trump-keep-coal-open",
    "summary": "",
    "source": "Canary Media",
    "date": "2025-09-04",
    "timestamp": "2025-09-04T01:24:04.711951",
    "categories": "policy,business,climate"
  },
  {
    "title": "5\n\nUSDA abruptly cancels rural energy grant application window",
    "link": "https://www.canarymedia.com/articles/clean-energy/usda-solar-rural-grants-uncertainty",
    "summary": "",
    "source": "Canary Media",
    "date": "2025-09-04",
    "timestamp": "2025-09-04T01:24:05.200091",
    "categories": "innovation,business"
  },
  {
    "title": "The incoherence of Trump\u2019s \u2018energy emergency\u2019",
    "link": "https://www.canarymedia.com/articles/politics/trump-energy-emergency-revolution-wind",
    "summary": "",
    "source": "Canary Media",
    "date": "2025-09-04",
    "timestamp": "2025-09-04T01:24:05.681836",
    "categories": "innovation,business"
  },
  {
    "title": "Chart: The retiring coal power plants Trump could revive",
    "link": "https://www.canarymedia.com/articles/fossil-fuels/coal-plants-trump-could-keep-open",
    "summary": "",
    "source": "Canary Media",
    "date": "2025-09-04",
    "timestamp": "2025-09-04T01:24:06.032077",
    "categories": "climate"
  },
  {
    "title": "Commonwealth Fusion raises nearly $1B to chase commercial fusion power",
    "link": "https://www.canarymedia.com/articles/nuclear/commonwealth-fusion-systems-series-b2-funding",
    "summary": "",
    "source": "Canary Media",
    "date": "2025-09-04",
    "timestamp": "2025-09-04T01:24:06.768576",
    "categories": "innovation,business"
  },
  {
    "title": "Trump extends order forcing Pennsylvania fossil-fuel plant to stay open",
    "link": "https://www.canarymedia.com/articles/fossil-fuels/trump-extend-pennsylvania-eddystone-stay-open-order",
    "summary": "",
    "source": "Canary Media",
    "date": "2025-09-04",
    "timestamp": "2025-09-04T01:24:07.306772",
    "categories": "innovation,business"
  },
  {
    "title": "Chart: Rooftop solar set to struggle under GOP tax credit repeal",
    "link": "https://www.canarymedia.com/articles/solar/chart-rooftop-solar-set-to-struggle-under-gop-tax-credit-repeal",
    "summary": "",
    "source": "Canary Media",
    "date": "2025-09-04",
    "timestamp": "2025-09-04T01:24:09.250444",
    "categories": "policy"
  },
  {
    "title": "Google\u2019s new plan to keep its data centers from stressing the grid",
    "link": "https://www.canarymedia.com/articles/utilities/google-ai-data-center-flexibility-help-grid",
    "summary": "",
    "source": "Canary Media",
    "date": "2025-09-04",
    "timestamp": "2025-09-04T01:24:10.169814",
    "categories": "innovation"
  },
  {
    "title": "What\u2019s the best time to buy an EV? Right now.",
    "link": "https://www.canarymedia.com/articles/electric-vehicles/buy-lease-ev-tax-credit",
    "summary": "",
    "source": "Canary Media",
    "date": "2025-09-04",
    "timestamp": "2025-09-04T01:24:12.771962",
    "categories": "innovation,business"
  },
  {
    "title": "North Carolina ditched its 2030 climate goal. Now what?",
    "link": "https://www.canarymedia.com/articles/emissions-reduction/north-carolina-ditch-duke-goal-now-what",
    "summary": "",
    "source": "Canary Media",
    "date": "2025-09-04",
    "timestamp": "2025-09-04T01:24:14.345044",
    "categories": "climate"
  },
  {
    "title": "US solar plant construction is on a record-breaking spree \u2014 for now",
    "link": "https://www.canarymedia.com/articles/solar/us-construction-record-breaking",
    "summary": "",
    "source": "Canary Media",
    "date": "2025-09-04",
    "timestamp": "2025-09-04T01:24:15.785802",
    "categories": "innovation,business"
  },
  {
    "title": "Halting Revolution Wind could be a\u00a0disaster for New England\u2019s grid",
    "link": "https://www.canarymedia.com/articles/offshore-wind/trump-revolution-halt-disaster-new-england-grid",
    "summary": "",
    "source": "Canary Media",
    "date": "2025-09-04",
    "timestamp": "2025-09-04T01:24:16.151272",
    "categories": "innovation"
  },
  {
    "title": "Trump admin\u2019s new anti-renewables rule rooted in fossil-fuel misinformation",
    "link": "https://www.canarymedia.com/articles/land-use/trump-interior-order-fossil-fuel-misinformation",
    "summary": "",
    "source": "Canary Media",
    "date": "2025-09-04",
    "timestamp": "2025-09-04T01:24:18.508187",
    "categories": "climate"
  }
]